{
  "id": "2026-07-27__susan-miller__0",
  "status": "scheduled",
  "page_id": "1029190046952177",
  "page_name": "Susan Miller",
  "topic": "storm",
  "format": "fact",
  "tier": "MID",
  "scheduled_date": "2026-07-27",
  "scheduled_time": "10:48",
  "message": "Last winter, I remember the evening the snowstorm was predicted to hit. I was busy making dinner when I suddenly thought, \"What if the power goes out?\" I quickly rummaged through my kitchen drawer and found a stash of candles and matches I had tucked away during a previous storm. \n\nI lit a few candles, and as the snow began to fall, I felt a cozy calm wash over me. Instead of worrying about what could happen, I brewed some hot cocoa and we all gathered around the table, sharing stories by candlelight. It turned into one of those rare family nights filled with laughter and warmth, despite the chilly chaos outside.\n\nThat little moment made me realize that sometimes, being prepared can lead to unexpected joys. A small win that saved the day! Have you had any little wins during a storm? Share your stories!",
  "image_path": "",
  "image_source": "none",
  "source_url": "",
  "link": "https://www.ready.gov/hurricanes",
  "post_id": "1029190046952177_122122067732744881",
  "error_reason": "",
  "body_hash": "26427d563ba2ff2c7203ccd02fe9b0718ef9f30ccfba627a4cbaffe4012396fd",
  "image_key": "gen"
}