{
  "id": "2026-06-27__jake-morrison__0",
  "status": "scheduled",
  "page_id": "768075889726058",
  "page_name": "Jake Morrison",
  "topic": "fire",
  "format": "fact",
  "tier": "DORMANT",
  "scheduled_date": "2026-06-27",
  "scheduled_time": "09:34",
  "message": "I've been reading through some solid fire safety basics lately, and honestly, a lot of it is just about knowing your exits and having a simple plan—nothing dramatic, just practical stuff that gives you peace of mind. There's a really helpful resource from Ready.gov that walks through the essentials in a straightforward way. What's one room in your home where you'd want to make sure everyone knows the quickest way out?",
  "image_path": "",
  "image_source": "none",
  "source_url": "",
  "link": "https://www.ready.gov/home-fires",
  "post_id": "768075889726058_122139901251028905",
  "error_reason": "",
  "body_hash": "87d942a5ea50835c641f957677c8f8f9ad32adb055e1aa7adfd7129349fc4e65",
  "image_key": "gen"
}