{
  "id": "2026-07-05__elizabeth-willis__0",
  "status": "scheduled",
  "page_id": "1092442657286729",
  "page_name": "Elizabeth Willis",
  "topic": "fire",
  "format": "fact",
  "tier": "DORMANT",
  "scheduled_date": "2026-07-05",
  "scheduled_time": "18:48",
  "message": "I've been diving into some solid fire safety basics lately, and honestly, it's way less overwhelming than I thought. There's this great resource from Ready.gov that walks through the practical stuff—like planning escape routes and testing smoke alarms—in a really straightforward way. The nice part is realizing that a lot of fire readiness is just common sense once you know what to focus on. What's one fire safety thing you've already tackled at home, or what's on your mental to-do list?",
  "image_path": "",
  "image_source": "none",
  "source_url": "",
  "link": "https://www.ready.gov/home-fires",
  "post_id": "1092442657286729_122117278124693329",
  "error_reason": "",
  "body_hash": "8694974733ccaadd9f09045e6975bb316382e07ba6339a5afc678be4f8bf7c57",
  "image_key": "gen"
}