{
  "id": "2026-07-18__stacy-peters__0",
  "status": "scheduled",
  "page_id": "1055885867606549",
  "page_name": "Stacy Peters",
  "topic": "preparedness",
  "format": "fact",
  "tier": "DORMANT",
  "scheduled_date": "2026-07-18",
  "scheduled_time": "10:59",
  "message": "Have you ever thought about what you'd need in an emergency? This resource is a great starting point to help you create a kit that suits your family's needs. It’s all about being ready for whatever life throws our way. What’s one thing you think should always be in an emergency kit?",
  "image_path": "",
  "image_source": "none",
  "source_url": "",
  "link": "https://www.ready.gov/kit",
  "post_id": "1055885867606549_122120041058848941",
  "error_reason": "",
  "body_hash": "739fa185e660869a3c80819e04ff7c3fdc9836689bab664569c72d52455db12b",
  "image_key": "gen"
}