{
  "id": "2026-06-24__lauren-gargulio__0",
  "status": "scheduled",
  "page_id": "1127031013825481",
  "page_name": "Lauren Gargulio",
  "topic": "storm",
  "format": "fact",
  "tier": "MID",
  "scheduled_date": "2026-06-24",
  "scheduled_time": "18:34",
  "message": "I've been thinking about how heat waves kind of sneak up on you—one day it's warm, the next day your AC is working overtime and you're worried about the whole family staying comfortable and safe. I found this straightforward resource that walks through the practical stuff: how to recognize heat exhaustion, what to keep on hand, and how to help neighbors who might be more vulnerable. Nothing scary, just solid information that makes me feel more prepared. Do you have a go-to way you keep your family cool during really hot spells?",
  "image_path": "",
  "image_source": "none",
  "source_url": "",
  "link": "https://www.ready.gov/heat",
  "post_id": "1127031013825481_122105137383335222",
  "error_reason": "",
  "body_hash": "405bff85bb899bd13977712c6291dcc8d953ef7832d315d0f43d4d2a71ca058c",
  "image_key": "gen"
}