{
  "id": "2026-06-29__tamika-jones__0",
  "status": "scheduled",
  "page_id": "1031788496687467",
  "page_name": "Tamika Jones",
  "topic": "storm",
  "format": "fact",
  "tier": "DORMANT",
  "scheduled_date": "2026-06-29",
  "scheduled_time": "19:32",
  "message": "Last spring, my partner laughed at me for keeping a printed checklist taped inside our hall closet. 'Who even does that anymore?' Fast forward to a surprise ice storm warning at midnight—no time to think, no scrolling through old texts trying to remember what we needed. I grabbed that checklist, we knocked out the essentials in 20 minutes, and honestly? It felt like the easiest storm prep we've ever done.\n\nTurns out that small bit of prep work—just having *something* written down and ready—takes so much of the mental scramble out of the moment. No second-guessing, no 'did we forget the flashlights?' Just calm and done.\n\nHave you found a simple prep habit that's actually stuck around and made a difference for you?",
  "image_path": "",
  "image_source": "none",
  "source_url": "",
  "link": "https://www.ready.gov/hurricanes",
  "post_id": "1031788496687467_122115877808849311",
  "error_reason": "",
  "body_hash": "507b7763bac4d83b048773ccedf52f50edd344d5c0041e3f9082d574f409b25d",
  "image_key": "gen"
}