{
  "id": "2026-07-20__steven-sampson__0",
  "status": "scheduled",
  "page_id": "1124746537378992",
  "page_name": "Steven Sampson",
  "topic": "fire",
  "format": "fact",
  "tier": "DORMANT",
  "scheduled_date": "2026-07-20",
  "scheduled_time": "14:53",
  "message": "You know that one friend who's always ready for anything? Well, I might be that friend in my circle! Just the other day, I was in the kitchen making dinner when I suddenly remembered the time I watched a cooking show that mentioned keeping a fire extinguisher nearby. So, there I was, pulling my little fire extinguisher out from under the sink just to feel a bit safer while sautéing veggies. My family laughed, but I reassured them that it’s better to be safe than sorry! \n\nAnd honestly, it sparked a great conversation about our family escape plan and checking smoke alarms. It’s all about those little reminders to stay prepared without being alarmed, right? \n\nHave you ever found yourself being the gloriously over-prepared one? What’s your go-to safety tip?",
  "image_path": "",
  "image_source": "none",
  "source_url": "",
  "link": "https://www.ready.gov/home-fires",
  "post_id": "1124746537378992_122115059810692122",
  "error_reason": "",
  "body_hash": "8994dd8c607ae88d7ad5ee79049b7ac7297c3dd48cb374b03e557282d268394d",
  "image_key": "gen"
}