{
  "id": "2026-07-30__lauren-gargulio__0",
  "status": "scheduled",
  "page_id": "1127031013825481",
  "page_name": "Lauren Gargulio",
  "topic": "storm",
  "format": "fact",
  "tier": "MID",
  "scheduled_date": "2026-07-30",
  "scheduled_time": "10:35",
  "message": "As we gear up for storm season, it's always good to have a reliable resource to guide us. Ready.gov offers practical tips on how to prepare for hurricanes that can help keep our families safe and sound. Have you ever made a storm preparedness plan? I'd love to hear what you include!",
  "image_path": "",
  "image_source": "none",
  "source_url": "",
  "link": "https://www.ready.gov/hurricanes",
  "post_id": "1127031013825481_122109812817335222",
  "error_reason": "",
  "body_hash": "2679be668ce94c15d8cc8c6ace0588cd9b376a202700eff20642954e4179d9b8",
  "image_key": "gen"
}