{
  "id": "2026-07-23__nancy-nichols__0",
  "status": "scheduled",
  "page_id": "939630525911349",
  "page_name": "Nancy Nichols",
  "topic": "dog",
  "format": "fact",
  "tier": "MID",
  "scheduled_date": "2026-07-23",
  "scheduled_time": "19:47",
  "message": "Hey friends! I recently came across a great resource that outlines how to create an emergency kit for your family, including our furry friends. It's a handy way to ensure everyone is prepared, and it’s never too early to start thinking ahead. What’s one item you think is a must-have in your emergency kit?",
  "image_path": "",
  "image_source": "none",
  "source_url": "",
  "link": "https://www.ready.gov/kit",
  "post_id": "939630525911349_122120458239024743",
  "error_reason": "",
  "body_hash": "458d219c824b61bcd288d01ba3f4e5a74feb87b46e53a7cdcc26806f723cff96",
  "image_key": "gen"
}