{
  "id": "2026-07-24__susan-mitchell__0",
  "status": "scheduled",
  "page_id": "719343644592338",
  "page_name": "Susan Mitchell",
  "topic": "preparedness",
  "format": "fact",
  "tier": "MID",
  "scheduled_date": "2026-07-24",
  "scheduled_time": "15:42",
  "message": "Building a well-stocked emergency kit is a fantastic step toward feeling more prepared for whatever life throws our way. This resource offers practical guidance on what to include, making it easier to start your own kit. Have you thought about what essentials you might need for your family?",
  "image_path": "",
  "image_source": "none",
  "source_url": "",
  "link": "https://www.ready.gov/kit",
  "post_id": "719343644592338_122191741676926262",
  "error_reason": "",
  "body_hash": "9cf50c3c4732a3c429989bb350f765ba80d926a43917bbeec8bff9fd6a530473",
  "image_key": "gen"
}