{
  "id": "2026-06-30__karen-keller__0",
  "status": "scheduled",
  "page_id": "1003918682810439",
  "page_name": "Karen Keller",
  "topic": "preparedness",
  "format": "fact",
  "tier": "HIGH",
  "scheduled_date": "2026-06-30",
  "scheduled_time": "15:31",
  "message": "I've been slowly building up my emergency kit over the past few months, and honestly it feels good to have the basics covered without stressing about it. I found this resource super helpful for figuring out what actually makes sense to keep on hand—nothing dramatic, just practical stuff you'd genuinely want if the power went out or you couldn't leave home for a few days. What's one item you already have at home that you'd definitely want to grab in a pinch?",
  "image_path": "",
  "image_source": "none",
  "source_url": "",
  "link": "https://www.ready.gov/kit",
  "post_id": "1003918682810439_122119991937072843",
  "error_reason": "",
  "body_hash": "8b4eaf7687b37fcfd20986e9cd771e16155b661be641f6ce73dc6dd00ac469cc",
  "image_key": "gen"
}