{
  "id": "2026-06-21__jake-morrison__0",
  "status": "scheduled",
  "page_id": "768075889726058",
  "page_name": "Jake Morrison",
  "topic": "fire",
  "format": "fact",
  "tier": "DORMANT",
  "scheduled_date": "2026-06-21",
  "scheduled_time": "09:28",
  "message": "I've been slowly working through my home prep checklist, and honestly, the fire safety stuff feels less overwhelming when you break it into actual steps instead of imagining worst-case scenarios. Found this solid resource from Ready.gov that walks through the practical basics—escape planning, smoke alarms, that kind of thing. Turns out a lot of it is pretty straightforward. What's one fire safety thing you've already got handled at your place?",
  "image_path": "",
  "image_source": "none",
  "source_url": "",
  "link": "https://www.ready.gov/home-fires",
  "post_id": "768075889726058_122139360429028905",
  "error_reason": "",
  "body_hash": "a8466f9733636d48cb7a4c444f73751d8eb00f64eba1c39d4f2db7b9da4909e8",
  "image_key": "gen"
}