{
  "id": "2026-07-20__abigail-adams__0",
  "status": "scheduled",
  "page_id": "911963812004163",
  "page_name": "Abigail Adams",
  "topic": "blackout",
  "format": "fact",
  "tier": "LOW",
  "scheduled_date": "2026-07-20",
  "scheduled_time": "13:39",
  "message": "We've all been there—suddenly, the lights go out, and it can feel a bit unsettling. The Red Cross has put together some really handy tips on how to prepare for a power outage so you can stay calm and collected. How do you like to pass the time when the power goes out?",
  "image_path": "",
  "image_source": "none",
  "source_url": "",
  "link": "https://www.redcross.org/get-help/how-to-prepare-for-emergencies/types-of-emergencies/power-outage.html",
  "post_id": "911963812004163_122134720839187534",
  "error_reason": "",
  "body_hash": "246ef6527a745d3c72f949aab169bdde1cf0cf20b5372a140b918eb88e89e740",
  "image_key": "gen"
}