{
  "id": "2026-06-29__the-family-readiness-project__0",
  "status": "scheduled",
  "page_id": "1059660273889438",
  "page_name": "The Family Readiness Project",
  "topic": "preparedness",
  "format": "fact",
  "tier": "MID",
  "scheduled_date": "2026-06-29",
  "scheduled_time": "15:42",
  "message": "So my partner and I had *that* conversation last week—the one where I'd mentioned keeping documents in a waterproof folder, and they'd kind of nodded and moved on. Then a pipe burst in the basement (minor, caught quickly, but still), and suddenly they were asking where we kept the insurance papers. I got to have the most satisfying, gentle 'I told you so' moment of my life. No gloating—just relief that we actually *knew* where things were. We spent an hour that evening making a simple list of what matters most and where it lives. Nothing fancy. Turns out there's something oddly comforting about knowing you've got your own back, even in small ways. Have you and your household ever had that click-moment where something finally felt worth doing?",
  "image_path": "",
  "image_source": "none",
  "source_url": "",
  "link": "https://www.ready.gov/kit",
  "post_id": "1059660273889438_122132473137281758",
  "error_reason": "",
  "body_hash": "f416b9f6a7aaf4e2dfcdc2baca79e3b3f80e22d86ddf7e2456caf67316e74130",
  "image_key": "gen"
}