{
  "id": "2026-07-25__bruna-lorrell__0",
  "status": "scheduled",
  "page_id": "1188071991047656",
  "page_name": "Bruna Lorrell",
  "topic": "storm",
  "format": "fact",
  "tier": "MID",
  "scheduled_date": "2026-07-25",
  "scheduled_time": "14:05",
  "message": "The other day, a big storm was forecasted, and my kids were buzzing with excitement—like it was Christmas Eve! Meanwhile, I was in full prep mode, shuffling around the house, checking supplies and making sure we were ready for whatever might come our way. \n\nI remember my youngest asking, ‘Why are you so worried, Mom? It’s just a little rain!’ I chuckled, realizing that their carefree spirit is a gift sometimes. But I also wanted them to understand the importance of being ready. So, we turned it into a family project! We gathered our flashlights, snacks, and board games, turning our storm prep into a fun little adventure. \n\nIt felt great to balance their excitement with a little calm preparedness. And honestly, I think we all learned something about looking out for one another, even when the skies are clear. \n\nHas your family ever turned a prep moment into a fun experience? Would love to hear your stories! Also, I found this little refresher helpful as we got ready.",
  "image_path": "",
  "image_source": "none",
  "source_url": "",
  "link": "https://www.ready.gov/heat",
  "post_id": "1188071991047656_122122626003350476",
  "error_reason": "",
  "body_hash": "3ad4f42e73b9e0a103f96b9ced9d3fd75f976629b344731af3e1f521af3147cf",
  "image_key": "gen"
}