{
  "id": "2026-06-03__diane-c-roberts__0",
  "status": "scheduled",
  "page_id": "1149657604892592",
  "page_name": "Diane C. Roberts",
  "topic": "cat",
  "tier": "HIGH",
  "scheduled_date": "2026-06-03",
  "scheduled_time": "08:35",
  "message": "\"But my cat never goes outside — does she really need the vet?\" 🩺🐱\n\nIt's one of the most common things cat parents believe, and it's worth gently setting straight: indoor cats need regular vet care just as much as outdoor cats do. Living inside protects them from a lot of dangers, but it doesn't make them immune to things like dental disease, kidney trouble, thyroid issues, arthritis, or weight gain.\n\nHere's the tricky part: cats are masters at hiding when they feel unwell. By the time something is obvious, it may have been brewing for a while. That's exactly why a yearly checkup matters — and twice a year for seniors (roughly 8+). These visits catch the quiet problems early, when they're easiest to treat.\n\nThink of it as the boring kind of love. 💛 The kind that keeps them purring on your lap for years to come.\n\nWhen was your cat's last checkup? 🐾",
  "image_path": "/Users/andreataVPS/pet-page-posts/state/work/2026-06-03__diane-c-roberts__0.png",
  "image_source": "generated",
  "source_url": "",
  "post_id": "122102610039338376",
  "error_reason": "",
  "body_hash": "dba8a157b26649ffa46eb79e92ecbb82b103f3e430e90dd8f8077eed651f3784",
  "image_key": "gen"
}