{
  "id": "2026-06-11__shoppingpaw__1",
  "status": "scheduled",
  "page_id": "763864950124903",
  "page_name": "ShoppingPaw",
  "topic": "dog",
  "format": "meme",
  "tier": "HIGH",
  "scheduled_date": "2026-06-11",
  "scheduled_time": "14:52",
  "message": "He had options. He chose violence — against this poor tree. 🐶🌳\n\nComment 🐾 if your dog refuses to bring home a normal-sized stick!",
  "image_path": "/Users/andreataVPS/pet-page-posts/state/work/2026-06-11__shoppingpaw__1.png",
  "image_source": "generated",
  "source_url": "",
  "post_id": "122180245070944514",
  "error_reason": "",
  "body_hash": "7c081725110dae5f0f8e84c75d601e0e5039cbc8e9148f33d33b47b5d78624aa",
  "image_key": "gen"
}