{
  "id": "2026-06-12__caroline-stones__0",
  "status": "scheduled",
  "page_id": "1201592776363278",
  "page_name": "Caroline Stones",
  "topic": "dog",
  "format": "fact",
  "tier": "DORMANT",
  "scheduled_date": "2026-06-12",
  "scheduled_time": "09:02",
  "message": "Here's one that sounds made up but is backed by real science: dogs prefer to poop facing north or south. 🐶🧭\n\nWhen researchers tracked 70 dogs across 37 different breeds — through nearly 1,900 poops — they found that on calm days, dogs tend to line their bodies up along the Earth's magnetic north–south axis to do their business, and avoid pointing east–west. The pattern only showed up when the magnetic field was steady, which is why nobody noticed it for so long.\n\nSo all that slow, sniffing, \"let me find the PERFECT spot\" routine before the big moment? Your dog might genuinely be consulting an internal compass you can't even feel. 🧭\n\nDoes your dog have an elaborate pre-poop ritual? Tell me about it below! 🐾",
  "image_path": "/Users/andreataVPS/pet-page-posts/state/work/2026-06-12__caroline-stones__0.png",
  "image_source": "generated",
  "source_url": "",
  "post_id": "122105351031340898",
  "error_reason": "",
  "body_hash": "fa68ca5dc3fa24959f393b4019cf8c71ae263be2a58ac97e17664da07567f16b",
  "image_key": "gen"
}